fds/__init__.py
fds/sdk/__init__.py
fds/sdk/FactSetQuantFactorLibrary/__init__.py
fds/sdk/FactSetQuantFactorLibrary/api_client.py
fds/sdk/FactSetQuantFactorLibrary/configuration.py
fds/sdk/FactSetQuantFactorLibrary/exceptions.py
fds/sdk/FactSetQuantFactorLibrary/model_utils.py
fds/sdk/FactSetQuantFactorLibrary/rest.py
fds/sdk/FactSetQuantFactorLibrary/api/__init__.py
fds/sdk/FactSetQuantFactorLibrary/api/factors_api.py
fds/sdk/FactSetQuantFactorLibrary/api/helper_api.py
fds/sdk/FactSetQuantFactorLibrary/apis/__init__.py
fds/sdk/FactSetQuantFactorLibrary/model/__init__.py
fds/sdk/FactSetQuantFactorLibrary/model/error_response.py
fds/sdk/FactSetQuantFactorLibrary/model/error_response_sub_errors.py
fds/sdk/FactSetQuantFactorLibrary/model/factor_groups_param.py
fds/sdk/FactSetQuantFactorLibrary/model/factors.py
fds/sdk/FactSetQuantFactorLibrary/model/factors_param.py
fds/sdk/FactSetQuantFactorLibrary/model/factors_request.py
fds/sdk/FactSetQuantFactorLibrary/model/factors_response.py
fds/sdk/FactSetQuantFactorLibrary/model/frequency.py
fds/sdk/FactSetQuantFactorLibrary/model/ids.py
fds/sdk/FactSetQuantFactorLibrary/model/library.py
fds/sdk/FactSetQuantFactorLibrary/model/library_request.py
fds/sdk/FactSetQuantFactorLibrary/model/library_response.py
fds/sdk/FactSetQuantFactorLibrary/models/__init__.py
fds.sdk.FactSetQuantFactorLibrary-1.1.0.dist-info/LICENSE
fds.sdk.FactSetQuantFactorLibrary-1.1.0.dist-info/METADATA
fds.sdk.FactSetQuantFactorLibrary-1.1.0.dist-info/WHEEL
fds.sdk.FactSetQuantFactorLibrary-1.1.0.dist-info/top_level.txt
fds.sdk.FactSetQuantFactorLibrary-1.1.0.dist-info/RECORD
